mscope/__init__.py
mscope/cfgloader.py
mscope/logg.py
mscope/mailgen.py
mscope/mailscan.py
mscope/main.py
mscope/utils01.py
mscope-0.1.3.dist-info/METADATA
mscope-0.1.3.dist-info/WHEEL
mscope-0.1.3.dist-info/entry_points.txt
mscope-0.1.3.dist-info/top_level.txt
mscope-0.1.3.dist-info/RECORD
