Metadata-Version: 2.4
Name: mscope
Version: 0.1.3
Summary: mscope allows you to find emails by username
Home-page: https://github.com/oakwide/mscope
Author: oakwide
Author-email: mscope@nomail.net
Classifier: Programming Language :: Python :: 3
Classifier: License :: OSI Approved :: GNU General Public License v3 (GPLv3)
Classifier: Operating System :: OS Independent
Requires-Python: >=3.6
Requires-Dist: requests
Requires-Dist: dnspython
Dynamic: author
Dynamic: author-email
Dynamic: classifier
Dynamic: description
Dynamic: description-content-type
Dynamic: home-page
Dynamic: requires-dist
Dynamic: requires-python
Dynamic: summary
